ims_utils/__init__.py
ims_utils/_version.py
ims_utils/baseline.py
ims_utils/deisotope.py
ims_utils/detect.py
ims_utils/fiducials.py
ims_utils/filters.py
ims_utils/html.py
ims_utils/internorm.py
ims_utils/kendrick.py
ims_utils/lockmass.py
ims_utils/peak_filter.py
ims_utils/profile.py
ims_utils/py.typed
ims_utils/resample.py
ims_utils/smooth.py
ims_utils/spectrum.py
ims_utils/utilities.py
ims_utils/_vendored/__init__.py
ims_utils/_vendored/kneed.py
ims_utils/_vendored/peakutils.py
ims_utils/_vendored/wavelets.py
ims_utils/assets/__init__.py
ims_utils/assets/matrix/dmaca;negative.csv
ims_utils/assets/matrix/mapca;negative.csv
ims_utils/assets/matrix/mapca;positive.csv
ims_utils/batchnorm/__init__.py
ims_utils/batchnorm/combat.py
ims_utils/batchnorm/recombat.py
ims_utils/batchnorm/utilities.py
ims_utils-0.1.8.dist-info/licenses/LICENSE
ims_utils-0.1.8.dist-info/METADATA
ims_utils-0.1.8.dist-info/WHEEL
ims_utils-0.1.8.dist-info/top_level.txt
ims_utils-0.1.8.dist-info/RECORD
